[
  {
    "code": "0000",
    "images": [
      {
        "name": "0000a.png",
        "width": 25,
        "height": 39,
        "x": 210,
        "y": 236,
        "z": 1700
      },
      {
        "name": "0000b.png",
        "width": 1,
        "height": 1,
        "x": 500,
        "y": 0,
        "z": 1100
      }
    ],
    "icon": "gunblader/belt/0000.png"
  },
  {
    "code": "0001",
    "name": "玄色战役腰饰",
    "images": [
      {
        "name": "0001a.png",
        "width": 25,
        "height": 39,
        "x": 210,
        "y": 236,
        "z": 1700
      },
      {
        "name": "0001b.png",
        "width": 1,
        "height": 1,
        "x": 500,
        "y": 0,
        "z": 1100
      }
    ],
    "icon": "gunblader/belt/0001.png"
  },
  {
    "code": "0100",
    "images": [
      {
        "name": "0100c.png",
        "width": 25,
        "height": 14,
        "x": 209,
        "y": 229,
        "z": 1950
      },
      {
        "name": "0100d.png",
        "width": 47,
        "height": 80,
        "x": 197,
        "y": 219,
        "z": 850
      }
    ],
    "icon": "gunblader/belt/0100.png"
  },
  {
    "code": "0101",
    "images": [
      {
        "name": "0101c.png",
        "width": 25,
        "height": 14,
        "x": 209,
        "y": 229,
        "z": 1950
      },
      {
        "name": "0101d.png",
        "width": 47,
        "height": 80,
        "x": 197,
        "y": 219,
        "z": 850
      }
    ],
    "icon": "gunblader/belt/0101.png"
  },
  {
    "code": "0102",
    "images": [
      {
        "name": "0102c.png",
        "width": 25,
        "height": 14,
        "x": 209,
        "y": 229,
        "z": 1950
      },
      {
        "name": "0102d.png",
        "width": 47,
        "height": 80,
        "x": 197,
        "y": 219,
        "z": 850
      }
    ],
    "icon": "gunblader/belt/0102.png"
  },
  {
    "code": "0103",
    "images": [
      {
        "name": "0103c.png",
        "width": 25,
        "height": 14,
        "x": 209,
        "y": 229,
        "z": 1950
      },
      {
        "name": "0103d.png",
        "width": 47,
        "height": 80,
        "x": 197,
        "y": 219,
        "z": 850
      }
    ],
    "icon": "gunblader/belt/0103.png"
  },
  {
    "code": "0104",
    "name": "海军风情远航长剑",
    "images": [
      {
        "name": "0104c.png",
        "width": 25,
        "height": 14,
        "x": 209,
        "y": 229,
        "z": 1950
      },
      {
        "name": "0104d.png",
        "width": 47,
        "height": 80,
        "x": 197,
        "y": 219,
        "z": 850
      }
    ],
    "icon": "gunblader/belt/0104.png"
  },
  {
    "code": "0300",
    "name": "圣诞欢歌红鼻雪人",
    "images": [
      {
        "name": "0300c.png",
        "width": 11,
        "height": 17,
        "x": 205,
        "y": 228,
        "z": 1950
      },
      {
        "name": "0300d.png",
        "width": 1,
        "height": 1,
        "x": 500,
        "y": 0,
        "z": 850
      }
    ],
    "icon": "gunblader/belt/0300.png"
  },
  {
    "code": "0301",
    "name": "圣诞欢歌黄鼻雪人",
    "images": [
      {
        "name": "0301c.png",
        "width": 11,
        "height": 17,
        "x": 205,
        "y": 228,
        "z": 1950
      },
      {
        "name": "0301d.png",
        "width": 1,
        "height": 1,
        "x": 500,
        "y": 0,
        "z": 850
      }
    ],
    "icon": "gunblader/belt/0301.png"
  },
  {
    "code": "0302",
    "name": "圣诞欢歌橘鼻雪人",
    "images": [
      {
        "name": "0302c.png",
        "width": 11,
        "height": 17,
        "x": 205,
        "y": 228,
        "z": 1950
      },
      {
        "name": "0302d.png",
        "width": 1,
        "height": 1,
        "x": 500,
        "y": 0,
        "z": 850
      }
    ],
    "icon": "gunblader/belt/0302.png"
  },
  {
    "code": "0400",
    "name": "兽人英雄银色骏马尾巴",
    "images": [
      {
        "name": "0400c.png",
        "width": 26,
        "height": 19,
        "x": 208,
        "y": 230,
        "z": 1950
      },
      {
        "name": "0400d.png",
        "width": 24,
        "height": 61,
        "x": 197,
        "y": 241,
        "z": 850
      }
    ],
    "icon": "gunblader/belt/0400.png"
  },
  {
    "code": "0401",
    "name": "兽人英雄金色骏马尾巴",
    "images": [
      {
        "name": "0401c.png",
        "width": 26,
        "height": 19,
        "x": 208,
        "y": 230,
        "z": 1950
      },
      {
        "name": "0401d.png",
        "width": 24,
        "height": 61,
        "x": 197,
        "y": 241,
        "z": 850
      }
    ],
    "icon": "gunblader/belt/0401.png"
  },
  {
    "code": "0402",
    "name": "兽人英雄米色骏马尾巴",
    "images": [
      {
        "name": "0402c.png",
        "width": 26,
        "height": 19,
        "x": 208,
        "y": 230,
        "z": 1950
      },
      {
        "name": "0402d.png",
        "width": 24,
        "height": 61,
        "x": 197,
        "y": 241,
        "z": 850
      }
    ],
    "icon": "gunblader/belt/0402.png"
  },
  {
    "code": "0403",
    "name": "兽人英雄浅棕骏马尾巴",
    "images": [
      {
        "name": "0403c.png",
        "width": 26,
        "height": 19,
        "x": 208,
        "y": 230,
        "z": 1950
      },
      {
        "name": "0403d.png",
        "width": 24,
        "height": 61,
        "x": 197,
        "y": 241,
        "z": 850
      }
    ],
    "icon": "gunblader/belt/0403.png"
  },
  {
    "code": "0500",
    "name": "驰风骑士银色腰链",
    "images": [
      {
        "name": "0500a.png",
        "width": 13,
        "height": 12,
        "x": 210,
        "y": 233,
        "z": 1700
      }
    ],
    "icon": "gunblader/belt/0500.png"
  },
  {
    "code": "0501",
    "name": "驰风骑士深色腰链",
    "images": [
      {
        "name": "0501a.png",
        "width": 13,
        "height": 12,
        "x": 210,
        "y": 233,
        "z": 1700
      }
    ],
    "icon": "gunblader/belt/0501.png"
  },
  {
    "code": "0502",
    "name": "驰风骑士蓝色腰链",
    "images": [
      {
        "name": "0502a.png",
        "width": 13,
        "height": 12,
        "x": 210,
        "y": 233,
        "z": 1700
      }
    ],
    "icon": "gunblader/belt/0502.png"
  },
  {
    "code": "0503",
    "name": "驰风骑士金色腰链",
    "images": [
      {
        "name": "0503a.png",
        "width": 13,
        "height": 12,
        "x": 210,
        "y": 233,
        "z": 1700
      }
    ],
    "icon": "gunblader/belt/0503.png"
  },
  {
    "code": "0600",
    "name": "腾龙之颂黑色腰带",
    "images": [
      {
        "name": "0600c.png",
        "width": 21,
        "height": 10,
        "x": 211,
        "y": 229,
        "z": 1950
      }
    ],
    "icon": "gunblader/belt/0600.png"
  },
  {
    "code": "0601",
    "name": "腾龙之颂蓝色腰带",
    "images": [
      {
        "name": "0601c.png",
        "width": 21,
        "height": 10,
        "x": 211,
        "y": 229,
        "z": 1950
      }
    ],
    "icon": "gunblader/belt/0601.png"
  },
  {
    "code": "0602",
    "name": "腾龙之颂墨色腰带",
    "images": [
      {
        "name": "0602c.png",
        "width": 21,
        "height": 10,
        "x": 211,
        "y": 229,
        "z": 1950
      }
    ],
    "icon": "gunblader/belt/0602.png"
  },
  {
    "code": "0603",
    "name": "腾龙之颂墨绿腰带",
    "images": [
      {
        "name": "0603c.png",
        "width": 21,
        "height": 10,
        "x": 211,
        "y": 229,
        "z": 1950
      }
    ],
    "icon": "gunblader/belt/0603.png"
  },
  {
    "code": "0700",
    "name": "暖冬绅士褐色腰带",
    "images": [
      {
        "name": "0700a.png",
        "width": 19,
        "height": 5,
        "x": 212,
        "y": 235,
        "z": 1700
      }
    ],
    "icon": "gunblader/belt/0700.png"
  },
  {
    "code": "0701",
    "name": "暖冬绅士红色腰带",
    "images": [
      {
        "name": "0701a.png",
        "width": 19,
        "height": 5,
        "x": 212,
        "y": 235,
        "z": 1700
      }
    ],
    "icon": "gunblader/belt/0701.png"
  },
  {
    "code": "0702",
    "name": "暖冬绅士暗色腰带",
    "images": [
      {
        "name": "0702a.png",
        "width": 19,
        "height": 5,
        "x": 212,
        "y": 235,
        "z": 1700
      }
    ],
    "icon": "gunblader/belt/0702.png"
  },
  {
    "code": "0703",
    "name": "暖冬绅士蓝色腰带",
    "images": [
      {
        "name": "0703a.png",
        "width": 19,
        "height": 5,
        "x": 212,
        "y": 235,
        "z": 1700
      }
    ],
    "icon": "gunblader/belt/0703.png"
  },
  {
    "code": "0800",
    "name": "绯樱之舞黑色长剑",
    "images": [
      {
        "name": "0800c.png",
        "width": 1,
        "height": 1,
        "x": 500,
        "y": 0,
        "z": 1950
      },
      {
        "name": "0800d.png",
        "width": 68,
        "height": 37,
        "x": 190,
        "y": 226,
        "z": 850
      }
    ],
    "icon": "gunblader/belt/0800.png"
  },
  {
    "code": "0801",
    "name": "绯樱之舞红色长剑",
    "images": [
      {
        "name": "0801c.png",
        "width": 1,
        "height": 1,
        "x": 500,
        "y": 0,
        "z": 1950
      },
      {
        "name": "0801d.png",
        "width": 68,
        "height": 37,
        "x": 190,
        "y": 226,
        "z": 850
      }
    ],
    "icon": "gunblader/belt/0801.png"
  },
  {
    "code": "0802",
    "name": "绯樱之舞藏青长剑",
    "images": [
      {
        "name": "0802c.png",
        "width": 1,
        "height": 1,
        "x": 500,
        "y": 0,
        "z": 1950
      },
      {
        "name": "0802d.png",
        "width": 68,
        "height": 37,
        "x": 190,
        "y": 226,
        "z": 850
      }
    ],
    "icon": "gunblader/belt/0802.png"
  },
  {
    "code": "0803",
    "name": "绯樱之舞白色长剑",
    "images": [
      {
        "name": "0803c.png",
        "width": 1,
        "height": 1,
        "x": 500,
        "y": 0,
        "z": 1950
      },
      {
        "name": "0803d.png",
        "width": 68,
        "height": 37,
        "x": 190,
        "y": 226,
        "z": 850
      }
    ],
    "icon": "gunblader/belt/0803.png"
  },
  {
    "code": "0900",
    "name": "游牧之国白色腰带",
    "images": [
      {
        "name": "0900c.png",
        "width": 31,
        "height": 42,
        "x": 210,
        "y": 233,
        "z": 1950
      },
      {
        "name": "0900d.png",
        "width": 1,
        "height": 1,
        "x": 500,
        "y": 0,
        "z": 850
      }
    ],
    "icon": "gunblader/belt/0900.png"
  },
  {
    "code": "0901",
    "name": "游牧之国黄色腰带",
    "images": [
      {
        "name": "0901c.png",
        "width": 31,
        "height": 42,
        "x": 210,
        "y": 233,
        "z": 1950
      },
      {
        "name": "0901d.png",
        "width": 1,
        "height": 1,
        "x": 500,
        "y": 0,
        "z": 850
      }
    ],
    "icon": "gunblader/belt/0901.png"
  },
  {
    "code": "0902",
    "name": "游牧之国黑色腰带",
    "images": [
      {
        "name": "0902c.png",
        "width": 31,
        "height": 42,
        "x": 210,
        "y": 233,
        "z": 1950
      },
      {
        "name": "0902d.png",
        "width": 1,
        "height": 1,
        "x": 500,
        "y": 0,
        "z": 850
      }
    ],
    "icon": "gunblader/belt/0902.png"
  },
  {
    "code": "0903",
    "name": "游牧之国红色腰带",
    "images": [
      {
        "name": "0903c.png",
        "width": 31,
        "height": 42,
        "x": 210,
        "y": 233,
        "z": 1950
      },
      {
        "name": "0903d.png",
        "width": 1,
        "height": 1,
        "x": 500,
        "y": 0,
        "z": 850
      }
    ],
    "icon": "gunblader/belt/0903.png"
  },
  {
    "code": "1100",
    "name": "小当家呛口芥末",
    "images": [
      {
        "name": "1100c.png",
        "width": 9,
        "height": 11,
        "x": 203,
        "y": 245,
        "z": 1950
      },
      {
        "name": "1100d.png",
        "width": 1,
        "height": 1,
        "x": 500,
        "y": 0,
        "z": 850
      }
    ],
    "icon": "gunblader/belt/1100.png"
  },
  {
    "code": "1101",
    "name": "阿拉德研磨芥末[B款]",
    "images": [
      {
        "name": "1101c.png",
        "width": 9,
        "height": 11,
        "x": 203,
        "y": 245,
        "z": 1950
      },
      {
        "name": "1101d.png",
        "width": 1,
        "height": 1,
        "x": 500,
        "y": 0,
        "z": 850
      }
    ],
    "icon": "gunblader/belt/1101.png"
  },
  {
    "code": "1102",
    "name": "阿拉德研磨芥末[C款]",
    "images": [
      {
        "name": "1102c.png",
        "width": 9,
        "height": 11,
        "x": 203,
        "y": 245,
        "z": 1950
      },
      {
        "name": "1102d.png",
        "width": 1,
        "height": 1,
        "x": 500,
        "y": 0,
        "z": 850
      }
    ],
    "icon": "gunblader/belt/1102.png"
  },
  {
    "code": "1300",
    "name": "绝命谍影黑色腰带",
    "images": [
      {
        "name": "1300c.png",
        "width": 31,
        "height": 25,
        "x": 205,
        "y": 233,
        "z": 1950
      },
      {
        "name": "1300d.png",
        "width": 75,
        "height": 33,
        "x": 182,
        "y": 231,
        "z": 850
      }
    ],
    "icon": "gunblader/belt/1300.png"
  },
  {
    "code": "1301",
    "name": "绝命谍影褐色腰带",
    "images": [
      {
        "name": "1301c.png",
        "width": 31,
        "height": 25,
        "x": 205,
        "y": 233,
        "z": 1950
      },
      {
        "name": "1301d.png",
        "width": 75,
        "height": 33,
        "x": 182,
        "y": 231,
        "z": 850
      }
    ],
    "icon": "gunblader/belt/1301.png"
  },
  {
    "code": "1302",
    "name": "绝命谍影暗蓝腰带",
    "images": [
      {
        "name": "1302c.png",
        "width": 31,
        "height": 25,
        "x": 205,
        "y": 233,
        "z": 1950
      },
      {
        "name": "1302d.png",
        "width": 75,
        "height": 33,
        "x": 182,
        "y": 231,
        "z": 850
      }
    ],
    "icon": "gunblader/belt/1302.png"
  },
  {
    "code": "1303",
    "name": "绝命谍影棕色腰带",
    "images": [
      {
        "name": "1303c.png",
        "width": 31,
        "height": 25,
        "x": 205,
        "y": 233,
        "z": 1950
      },
      {
        "name": "1303d.png",
        "width": 75,
        "height": 33,
        "x": 182,
        "y": 231,
        "z": 850
      }
    ],
    "icon": "gunblader/belt/1303.png"
  },
  {
    "code": "1400",
    "name": "统御者银色怀表",
    "images": [
      {
        "name": "1400b.png",
        "width": 1,
        "height": 1,
        "x": 500,
        "y": 0,
        "z": 1100
      },
      {
        "name": "1400c.png",
        "width": 15,
        "height": 15,
        "x": 207,
        "y": 235,
        "z": 1950
      },
      {
        "name": "1400d.png",
        "width": 1,
        "height": 1,
        "x": 500,
        "y": 0,
        "z": 850
      }
    ],
    "icon": "gunblader/belt/1400.png"
  },
  {
    "code": "1401",
    "name": "统御者金色怀表",
    "images": [
      {
        "name": "1401b.png",
        "width": 1,
        "height": 1,
        "x": 500,
        "y": 0,
        "z": 1100
      },
      {
        "name": "1401c.png",
        "width": 15,
        "height": 15,
        "x": 207,
        "y": 235,
        "z": 1950
      },
      {
        "name": "1401d.png",
        "width": 1,
        "height": 1,
        "x": 500,
        "y": 0,
        "z": 850
      }
    ],
    "icon": "gunblader/belt/1401.png"
  },
  {
    "code": "1402",
    "name": "统御者紫粉怀表",
    "images": [
      {
        "name": "1402b.png",
        "width": 1,
        "height": 1,
        "x": 500,
        "y": 0,
        "z": 1100
      },
      {
        "name": "1402c.png",
        "width": 15,
        "height": 15,
        "x": 207,
        "y": 235,
        "z": 1950
      },
      {
        "name": "1402d.png",
        "width": 1,
        "height": 1,
        "x": 500,
        "y": 0,
        "z": 850
      }
    ],
    "icon": "gunblader/belt/1402.png"
  },
  {
    "code": "1403",
    "name": "统御者暖白怀表",
    "images": [
      {
        "name": "1403b.png",
        "width": 1,
        "height": 1,
        "x": 500,
        "y": 0,
        "z": 1100
      },
      {
        "name": "1403c.png",
        "width": 15,
        "height": 15,
        "x": 207,
        "y": 235,
        "z": 1950
      },
      {
        "name": "1403d.png",
        "width": 1,
        "height": 1,
        "x": 500,
        "y": 0,
        "z": 850
      }
    ],
    "icon": "gunblader/belt/1403.png"
  },
  {
    "code": "1500",
    "name": "源力掌控者蓝色腰带",
    "images": [
      {
        "name": "1500a.png",
        "width": 27,
        "height": 25,
        "x": 205,
        "y": 235,
        "z": 1700
      },
      {
        "name": "1500d.png",
        "width": 3,
        "height": 32,
        "x": 232,
        "y": 239,
        "z": 850
      }
    ],
    "icon": "gunblader/belt/1500.png"
  },
  {
    "code": "1501",
    "name": "源力掌控者紫色腰带",
    "images": [
      {
        "name": "1501a.png",
        "width": 27,
        "height": 25,
        "x": 205,
        "y": 235,
        "z": 1700
      },
      {
        "name": "1501d.png",
        "width": 3,
        "height": 32,
        "x": 232,
        "y": 239,
        "z": 850
      }
    ],
    "icon": "gunblader/belt/1501.png"
  },
  {
    "code": "1502",
    "name": "源力掌控者绿色腰带",
    "images": [
      {
        "name": "1502a.png",
        "width": 27,
        "height": 25,
        "x": 205,
        "y": 235,
        "z": 1700
      },
      {
        "name": "1502d.png",
        "width": 3,
        "height": 32,
        "x": 232,
        "y": 239,
        "z": 850
      }
    ],
    "icon": "gunblader/belt/1502.png"
  },
  {
    "code": "1503",
    "name": "源力掌控者橘色腰带",
    "images": [
      {
        "name": "1503a.png",
        "width": 27,
        "height": 25,
        "x": 205,
        "y": 235,
        "z": 1700
      },
      {
        "name": "1503d.png",
        "width": 3,
        "height": 32,
        "x": 232,
        "y": 239,
        "z": 850
      }
    ],
    "icon": "gunblader/belt/1503.png"
  },
  {
    "code": "1600",
    "name": "战场王牌褐色腰带",
    "images": [
      {
        "name": "1600b.png",
        "width": 3,
        "height": 14,
        "x": 232,
        "y": 238,
        "z": 1100
      },
      {
        "name": "1600c.png",
        "width": 30,
        "height": 34,
        "x": 203,
        "y": 231,
        "z": 1950
      },
      {
        "name": "1600d.png",
        "width": 1,
        "height": 1,
        "x": 500,
        "y": 0,
        "z": 850
      }
    ],
    "icon": "gunblader/belt/1600.png"
  },
  {
    "code": "1601",
    "name": "战场王牌红色腰带",
    "images": [
      {
        "name": "1601b.png",
        "width": 3,
        "height": 14,
        "x": 232,
        "y": 238,
        "z": 1100
      },
      {
        "name": "1601c.png",
        "width": 30,
        "height": 34,
        "x": 203,
        "y": 231,
        "z": 1950
      },
      {
        "name": "1601d.png",
        "width": 1,
        "height": 1,
        "x": 500,
        "y": 0,
        "z": 850
      }
    ],
    "icon": "gunblader/belt/1601.png"
  },
  {
    "code": "1602",
    "name": "战场王牌白色腰带",
    "images": [
      {
        "name": "1602b.png",
        "width": 3,
        "height": 14,
        "x": 232,
        "y": 238,
        "z": 1100
      },
      {
        "name": "1602c.png",
        "width": 30,
        "height": 34,
        "x": 203,
        "y": 231,
        "z": 1950
      },
      {
        "name": "1602d.png",
        "width": 1,
        "height": 1,
        "x": 500,
        "y": 0,
        "z": 850
      }
    ],
    "icon": "gunblader/belt/1602.png"
  },
  {
    "code": "1603",
    "name": "战场王牌暗蓝腰带",
    "images": [
      {
        "name": "1603b.png",
        "width": 3,
        "height": 14,
        "x": 232,
        "y": 238,
        "z": 1100
      },
      {
        "name": "1603c.png",
        "width": 30,
        "height": 34,
        "x": 203,
        "y": 231,
        "z": 1950
      },
      {
        "name": "1603d.png",
        "width": 1,
        "height": 1,
        "x": 500,
        "y": 0,
        "z": 850
      }
    ],
    "icon": "gunblader/belt/1603.png"
  },
  {
    "code": "1700",
    "images": [
      {
        "name": "1700c.png",
        "width": 45,
        "height": 68,
        "x": 195,
        "y": 224,
        "z": 1950
      },
      {
        "name": "1700d.png",
        "width": 20,
        "height": 17,
        "x": 215,
        "y": 257,
        "z": 850
      }
    ],
    "icon": "gunblader/belt/1700.png"
  },
  {
    "code": "1701",
    "name": "丹霞逍遥寰宇腰带",
    "images": [
      {
        "name": "1701c.png",
        "width": 45,
        "height": 68,
        "x": 195,
        "y": 224,
        "z": 1950
      },
      {
        "name": "1701d.png",
        "width": 20,
        "height": 17,
        "x": 215,
        "y": 257,
        "z": 850
      }
    ],
    "icon": "gunblader/belt/1701.png"
  },
  {
    "code": "1704",
    "name": "星海逍遥寰宇腰带",
    "images": [
      {
        "name": "1704c.png",
        "width": 45,
        "height": 68,
        "x": 195,
        "y": 224,
        "z": 1950
      },
      {
        "name": "1704d.png",
        "width": 20,
        "height": 17,
        "x": 215,
        "y": 257,
        "z": 850
      }
    ],
    "icon": "gunblader/belt/1704.png"
  },
  {
    "code": "1800",
    "name": "夜阑东皇之威长剑",
    "images": [
      {
        "name": "1800c.png",
        "width": 1,
        "height": 1,
        "x": 500,
        "y": 0,
        "z": 1950
      },
      {
        "name": "1800d.png",
        "width": 82,
        "height": 60,
        "x": 173,
        "y": 222,
        "z": 850
      }
    ],
    "icon": "gunblader/belt/1800.png"
  },
  {
    "code": "1802",
    "name": "拂晓东皇之威长剑",
    "images": [
      {
        "name": "1802c.png",
        "width": 1,
        "height": 1,
        "x": 500,
        "y": 0,
        "z": 1950
      },
      {
        "name": "1802d.png",
        "width": 82,
        "height": 60,
        "x": 173,
        "y": 222,
        "z": 850
      }
    ],
    "icon": "gunblader/belt/1802.png"
  },
  {
    "code": "1900",
    "name": "逝魔之力蓝色腰带",
    "images": [
      {
        "name": "1900c.png",
        "width": 32,
        "height": 35,
        "x": 203,
        "y": 227,
        "z": 1950
      },
      {
        "name": "1900d.png",
        "width": 1,
        "height": 1,
        "x": 500,
        "y": 0,
        "z": 850
      }
    ],
    "icon": "gunblader/belt/1900.png"
  },
  {
    "code": "1901",
    "name": "逝魔之力金色腰带",
    "images": [
      {
        "name": "1901c.png",
        "width": 32,
        "height": 35,
        "x": 203,
        "y": 227,
        "z": 1950
      },
      {
        "name": "1901d.png",
        "width": 1,
        "height": 1,
        "x": 500,
        "y": 0,
        "z": 850
      }
    ],
    "icon": "gunblader/belt/1901.png"
  },
  {
    "code": "1902",
    "name": "逝魔之力红色腰带",
    "images": [
      {
        "name": "1902c.png",
        "width": 32,
        "height": 35,
        "x": 203,
        "y": 227,
        "z": 1950
      },
      {
        "name": "1902d.png",
        "width": 1,
        "height": 1,
        "x": 500,
        "y": 0,
        "z": 850
      }
    ],
    "icon": "gunblader/belt/1902.png"
  },
  {
    "code": "1903",
    "name": "逝魔之力黄色腰带",
    "images": [
      {
        "name": "1903c.png",
        "width": 32,
        "height": 35,
        "x": 203,
        "y": 227,
        "z": 1950
      },
      {
        "name": "1903d.png",
        "width": 1,
        "height": 1,
        "x": 500,
        "y": 0,
        "z": 850
      }
    ],
    "icon": "gunblader/belt/1903.png"
  },
  {
    "code": "2000",
    "name": "荷鲁斯白色腰带",
    "images": [
      {
        "name": "2000c.png",
        "width": 31,
        "height": 39,
        "x": 204,
        "y": 231,
        "z": 1950
      }
    ],
    "icon": "gunblader/belt/2000.png"
  },
  {
    "code": "2001",
    "name": "荷鲁斯黑色腰带",
    "images": [
      {
        "name": "2001c.png",
        "width": 31,
        "height": 39,
        "x": 204,
        "y": 231,
        "z": 1950
      }
    ],
    "icon": "gunblader/belt/2001.png"
  },
  {
    "code": "2002",
    "name": "荷鲁斯深棕腰带",
    "images": [
      {
        "name": "2002c.png",
        "width": 31,
        "height": 39,
        "x": 204,
        "y": 231,
        "z": 1950
      }
    ],
    "icon": "gunblader/belt/2002.png"
  },
  {
    "code": "2003",
    "name": "荷鲁斯褐色腰带",
    "images": [
      {
        "name": "2003c.png",
        "width": 31,
        "height": 39,
        "x": 204,
        "y": 231,
        "z": 1950
      }
    ],
    "icon": "gunblader/belt/2003.png"
  },
  {
    "code": "2100",
    "name": "幻想诗篇银色腰甲",
    "images": [
      {
        "name": "2100c.png",
        "width": 31,
        "height": 24,
        "x": 205,
        "y": 231,
        "z": 1950
      },
      {
        "name": "2100d.png",
        "width": 1,
        "height": 1,
        "x": 500,
        "y": 0,
        "z": 850
      }
    ],
    "icon": "gunblader/belt/2100.png"
  },
  {
    "code": "2101",
    "name": "幻想诗篇金色腰甲",
    "images": [
      {
        "name": "2101c.png",
        "width": 31,
        "height": 24,
        "x": 205,
        "y": 231,
        "z": 1950
      },
      {
        "name": "2101d.png",
        "width": 1,
        "height": 1,
        "x": 500,
        "y": 0,
        "z": 850
      }
    ],
    "icon": "gunblader/belt/2101.png"
  },
  {
    "code": "2102",
    "name": "幻想诗篇亮金腰甲",
    "images": [
      {
        "name": "2102c.png",
        "width": 31,
        "height": 24,
        "x": 205,
        "y": 231,
        "z": 1950
      },
      {
        "name": "2102d.png",
        "width": 1,
        "height": 1,
        "x": 500,
        "y": 0,
        "z": 850
      }
    ],
    "icon": "gunblader/belt/2102.png"
  },
  {
    "code": "2103",
    "name": "幻想诗篇酷白腰甲",
    "images": [
      {
        "name": "2103c.png",
        "width": 31,
        "height": 24,
        "x": 205,
        "y": 231,
        "z": 1950
      },
      {
        "name": "2103d.png",
        "width": 1,
        "height": 1,
        "x": 500,
        "y": 0,
        "z": 850
      }
    ],
    "icon": "gunblader/belt/2103.png"
  },
  {
    "code": "2200",
    "name": "哈林匿名者腰带[A款]",
    "images": [
      {
        "name": "2200c.png",
        "width": 22,
        "height": 14,
        "x": 210,
        "y": 230,
        "z": 1950
      }
    ],
    "icon": "gunblader/belt/2200.png"
  },
  {
    "code": "2201",
    "name": "哈林匿名者腰带[B款]",
    "images": [
      {
        "name": "2201c.png",
        "width": 22,
        "height": 14,
        "x": 210,
        "y": 230,
        "z": 1950
      }
    ],
    "icon": "gunblader/belt/2201.png"
  },
  {
    "code": "2202",
    "name": "哈林匿名者腰带[C款]",
    "images": [
      {
        "name": "2202c.png",
        "width": 22,
        "height": 14,
        "x": 210,
        "y": 230,
        "z": 1950
      }
    ],
    "icon": "gunblader/belt/2202.png"
  },
  {
    "code": "2203",
    "name": "哈林匿名者腰带[D款]",
    "images": [
      {
        "name": "2203c.png",
        "width": 22,
        "height": 14,
        "x": 210,
        "y": 230,
        "z": 1950
      }
    ],
    "icon": "gunblader/belt/2203.png"
  },
  {
    "code": "2300",
    "name": "暗影锋铄寒星腰带",
    "images": [
      {
        "name": "2300c.png",
        "width": 37,
        "height": 37,
        "x": 200,
        "y": 228,
        "z": 1950
      },
      {
        "name": "2300d.png",
        "width": 1,
        "height": 1,
        "x": 500,
        "y": 0,
        "z": 850
      }
    ],
    "icon": "gunblader/belt/2300.png"
  },
  {
    "code": "2301",
    "name": "流光锋铄寒星腰带",
    "images": [
      {
        "name": "2301c.png",
        "width": 37,
        "height": 37,
        "x": 200,
        "y": 228,
        "z": 1950
      },
      {
        "name": "2301d.png",
        "width": 1,
        "height": 1,
        "x": 500,
        "y": 0,
        "z": 850
      }
    ],
    "icon": "gunblader/belt/2301.png"
  },
  {
    "code": "2302",
    "name": "墨魂锋铄寒星腰带",
    "images": [
      {
        "name": "2302c.png",
        "width": 37,
        "height": 37,
        "x": 200,
        "y": 228,
        "z": 1950
      },
      {
        "name": "2302d.png",
        "width": 1,
        "height": 1,
        "x": 500,
        "y": 0,
        "z": 850
      }
    ],
    "icon": "gunblader/belt/2302.png"
  },
  {
    "code": "2303",
    "name": "语风戮天之影腰带",
    "images": [
      {
        "name": "2303c.png",
        "width": 37,
        "height": 37,
        "x": 200,
        "y": 228,
        "z": 1950
      },
      {
        "name": "2303d.png",
        "width": 1,
        "height": 1,
        "x": 500,
        "y": 0,
        "z": 850
      }
    ],
    "icon": "gunblader/belt/2303.png"
  },
  {
    "code": "2304",
    "name": "炫彩戮天之影腰带",
    "images": [
      {
        "name": "2304c.png",
        "width": 37,
        "height": 37,
        "x": 200,
        "y": 228,
        "z": 1950
      },
      {
        "name": "2304d.png",
        "width": 1,
        "height": 1,
        "x": 500,
        "y": 0,
        "z": 850
      }
    ],
    "icon": "gunblader/belt/2304.png"
  },
  {
    "code": "2400",
    "name": "萌动兽语腰饰[A款]",
    "images": [
      {
        "name": "2400c.png",
        "width": 36,
        "height": 29,
        "x": 202,
        "y": 239,
        "z": 1950
      },
      {
        "name": "2400d.png",
        "width": 1,
        "height": 1,
        "x": 500,
        "y": 0,
        "z": 850
      }
    ],
    "icon": "gunblader/belt/2400.png"
  },
  {
    "code": "2401",
    "name": "萌动兽语腰饰[B款]",
    "images": [
      {
        "name": "2401c.png",
        "width": 36,
        "height": 29,
        "x": 202,
        "y": 239,
        "z": 1950
      },
      {
        "name": "2401d.png",
        "width": 1,
        "height": 1,
        "x": 500,
        "y": 0,
        "z": 850
      }
    ],
    "icon": "gunblader/belt/2401.png"
  },
  {
    "code": "2402",
    "name": "萌动兽语腰饰[C款]",
    "images": [
      {
        "name": "2402c.png",
        "width": 36,
        "height": 29,
        "x": 202,
        "y": 239,
        "z": 1950
      },
      {
        "name": "2402d.png",
        "width": 1,
        "height": 1,
        "x": 500,
        "y": 0,
        "z": 850
      }
    ],
    "icon": "gunblader/belt/2402.png"
  },
  {
    "code": "2500",
    "name": "皇者白色极道非道腰带 (特等)",
    "images": [
      {
        "name": "2500c.png",
        "width": 1,
        "height": 1,
        "x": 500,
        "y": 0,
        "z": 1950
      },
      {
        "name": "2500d.png",
        "width": 58,
        "height": 75,
        "x": 190,
        "y": 216,
        "z": 850
      }
    ],
    "icon": "gunblader/belt/2500.png"
  },
  {
    "code": "2501",
    "name": "皇者金色极道非道腰带 (特等)",
    "images": [
      {
        "name": "2501c.png",
        "width": 1,
        "height": 1,
        "x": 500,
        "y": 0,
        "z": 1950
      },
      {
        "name": "2501d.png",
        "width": 58,
        "height": 75,
        "x": 190,
        "y": 216,
        "z": 850
      }
    ],
    "icon": "gunblader/belt/2501.png"
  },
  {
    "code": "2502",
    "name": "皇者黑色极道非道腰带 (特等)",
    "images": [
      {
        "name": "2502c.png",
        "width": 1,
        "height": 1,
        "x": 500,
        "y": 0,
        "z": 1950
      },
      {
        "name": "2502d.png",
        "width": 58,
        "height": 75,
        "x": 190,
        "y": 216,
        "z": 850
      }
    ],
    "icon": "gunblader/belt/2502.png"
  },
  {
    "code": "2600",
    "name": "飒舞之灵佑绿色腰甲",
    "images": [
      {
        "name": "2600c.png",
        "width": 57,
        "height": 73,
        "x": 187,
        "y": 228,
        "z": 1950
      },
      {
        "name": "2600d.png",
        "width": 25,
        "height": 24,
        "x": 211,
        "y": 262,
        "z": 850
      }
    ],
    "icon": "gunblader/belt/2600.png"
  },
  {
    "code": "2601",
    "name": "飒舞之灵佑黄色腰甲",
    "images": [
      {
        "name": "2601c.png",
        "width": 57,
        "height": 73,
        "x": 187,
        "y": 228,
        "z": 1950
      },
      {
        "name": "2601d.png",
        "width": 25,
        "height": 24,
        "x": 211,
        "y": 262,
        "z": 850
      }
    ],
    "icon": "gunblader/belt/2601.png"
  },
  {
    "code": "2602",
    "name": "飒舞之灵佑黑色腰甲",
    "images": [
      {
        "name": "2602c.png",
        "width": 57,
        "height": 73,
        "x": 187,
        "y": 228,
        "z": 1950
      },
      {
        "name": "2602d.png",
        "width": 25,
        "height": 24,
        "x": 211,
        "y": 262,
        "z": 850
      }
    ],
    "icon": "gunblader/belt/2602.png"
  },
  {
    "code": "2603",
    "name": "飒舞之灵佑红色腰甲",
    "images": [
      {
        "name": "2603c.png",
        "width": 57,
        "height": 73,
        "x": 187,
        "y": 228,
        "z": 1950
      },
      {
        "name": "2603d.png",
        "width": 25,
        "height": 24,
        "x": 211,
        "y": 262,
        "z": 850
      }
    ],
    "icon": "gunblader/belt/2603.png"
  },
  {
    "code": "2700",
    "name": "小奶猪尾巴",
    "images": [
      {
        "name": "2700c.png",
        "width": 21,
        "height": 13,
        "x": 210,
        "y": 229,
        "z": 1950
      },
      {
        "name": "2700d.png",
        "width": 7,
        "height": 15,
        "x": 204,
        "y": 239,
        "z": 850
      }
    ],
    "icon": "gunblader/belt/2700.png"
  },
  {
    "code": "2701",
    "name": "小金猪尾巴",
    "images": [
      {
        "name": "2701c.png",
        "width": 21,
        "height": 13,
        "x": 210,
        "y": 229,
        "z": 1950
      },
      {
        "name": "2701d.png",
        "width": 7,
        "height": 15,
        "x": 204,
        "y": 239,
        "z": 850
      }
    ],
    "icon": "gunblader/belt/2701.png"
  },
  {
    "code": "2702",
    "name": "小黑猪尾巴",
    "images": [
      {
        "name": "2702c.png",
        "width": 21,
        "height": 13,
        "x": 210,
        "y": 229,
        "z": 1950
      },
      {
        "name": "2702d.png",
        "width": 7,
        "height": 15,
        "x": 204,
        "y": 239,
        "z": 850
      }
    ],
    "icon": "gunblader/belt/2702.png"
  },
  {
    "code": "2703",
    "name": "小粉猪尾巴",
    "images": [
      {
        "name": "2703c.png",
        "width": 21,
        "height": 13,
        "x": 210,
        "y": 229,
        "z": 1950
      },
      {
        "name": "2703d.png",
        "width": 7,
        "height": 15,
        "x": 204,
        "y": 239,
        "z": 850
      }
    ],
    "icon": "gunblader/belt/2703.png"
  },
  {
    "code": "2800",
    "name": "弑心镇魂者风归云腰带[A款]",
    "images": [
      {
        "name": "2800b.png",
        "width": 17,
        "height": 31,
        "x": 231,
        "y": 212,
        "z": 1100
      },
      {
        "name": "2800c.png",
        "width": 37,
        "height": 31,
        "x": 196,
        "y": 230,
        "z": 1950
      },
      {
        "name": "2800d.png",
        "width": 21,
        "height": 35,
        "x": 215,
        "y": 242,
        "z": 850
      }
    ],
    "icon": "gunblader/belt/2800.png"
  },
  {
    "code": "2801",
    "name": "弑心镇魂者风归云腰带[B款]",
    "images": [
      {
        "name": "2801b.png",
        "width": 17,
        "height": 31,
        "x": 231,
        "y": 212,
        "z": 1100
      },
      {
        "name": "2801c.png",
        "width": 37,
        "height": 31,
        "x": 196,
        "y": 230,
        "z": 1950
      },
      {
        "name": "2801d.png",
        "width": 21,
        "height": 35,
        "x": 215,
        "y": 242,
        "z": 850
      }
    ],
    "icon": "gunblader/belt/2801.png"
  },
  {
    "code": "2802",
    "name": "弑心镇魂者风归云腰带[C款]",
    "images": [
      {
        "name": "2802b.png",
        "width": 17,
        "height": 31,
        "x": 231,
        "y": 212,
        "z": 1100
      },
      {
        "name": "2802c.png",
        "width": 37,
        "height": 31,
        "x": 196,
        "y": 230,
        "z": 1950
      },
      {
        "name": "2802d.png",
        "width": 21,
        "height": 35,
        "x": 215,
        "y": 242,
        "z": 850
      }
    ],
    "icon": "gunblader/belt/2802.png"
  },
  {
    "code": "2803",
    "name": "弑心镇魂者风归云腰带[D款]",
    "images": [
      {
        "name": "2803b.png",
        "width": 17,
        "height": 31,
        "x": 231,
        "y": 212,
        "z": 1100
      },
      {
        "name": "2803c.png",
        "width": 37,
        "height": 31,
        "x": 196,
        "y": 230,
        "z": 1950
      },
      {
        "name": "2803d.png",
        "width": 21,
        "height": 35,
        "x": 215,
        "y": 242,
        "z": 850
      }
    ],
    "icon": "gunblader/belt/2803.png"
  },
  {
    "code": "2900",
    "name": "未来开拓者应天歌腰带[A款]",
    "images": [
      {
        "name": "2900c.png",
        "width": 28,
        "height": 31,
        "x": 205,
        "y": 229,
        "z": 1950
      },
      {
        "name": "2900d.png",
        "width": 1,
        "height": 1,
        "x": 500,
        "y": 0,
        "z": 850
      }
    ],
    "icon": "gunblader/belt/2900.png"
  },
  {
    "code": "2901",
    "name": "未来开拓者应天歌腰带[B款]",
    "images": [
      {
        "name": "2901c.png",
        "width": 28,
        "height": 31,
        "x": 205,
        "y": 229,
        "z": 1950
      },
      {
        "name": "2901d.png",
        "width": 1,
        "height": 1,
        "x": 500,
        "y": 0,
        "z": 850
      }
    ],
    "icon": "gunblader/belt/2901.png"
  },
  {
    "code": "2902",
    "name": "未来开拓者应天歌腰带[C款]",
    "images": [
      {
        "name": "2902c.png",
        "width": 28,
        "height": 31,
        "x": 205,
        "y": 229,
        "z": 1950
      },
      {
        "name": "2902d.png",
        "width": 1,
        "height": 1,
        "x": 500,
        "y": 0,
        "z": 850
      }
    ],
    "icon": "gunblader/belt/2902.png"
  },
  {
    "code": "2903",
    "name": "未来开拓者应天歌腰带[D款]",
    "images": [
      {
        "name": "2903c.png",
        "width": 28,
        "height": 31,
        "x": 205,
        "y": 229,
        "z": 1950
      },
      {
        "name": "2903d.png",
        "width": 1,
        "height": 1,
        "x": 500,
        "y": 0,
        "z": 850
      }
    ],
    "icon": "gunblader/belt/2903.png"
  },
  {
    "code": "3000",
    "name": "威尔海姆的蓝色腰带",
    "images": [
      {
        "name": "3000a.png",
        "width": 19,
        "height": 7,
        "x": 212,
        "y": 233,
        "z": 1700
      }
    ],
    "icon": "gunblader/belt/3000.png"
  },
  {
    "code": "3100",
    "name": "化装舞会凯恩棕色双剑",
    "images": [
      {
        "name": "3100c.png",
        "width": 1,
        "height": 1,
        "x": 500,
        "y": 0,
        "z": 1950
      },
      {
        "name": "3100d.png",
        "width": 68,
        "height": 58,
        "x": 176,
        "y": 224,
        "z": 850
      }
    ],
    "icon": "gunblader/belt/3100.png"
  },
  {
    "code": "3101",
    "name": "化装舞会凯恩红色双剑",
    "images": [
      {
        "name": "3101c.png",
        "width": 1,
        "height": 1,
        "x": 500,
        "y": 0,
        "z": 1950
      },
      {
        "name": "3101d.png",
        "width": 68,
        "height": 58,
        "x": 176,
        "y": 224,
        "z": 850
      }
    ],
    "icon": "gunblader/belt/3101.png"
  },
  {
    "code": "3102",
    "name": "化装舞会凯恩紫色双剑",
    "images": [
      {
        "name": "3102c.png",
        "width": 1,
        "height": 1,
        "x": 500,
        "y": 0,
        "z": 1950
      },
      {
        "name": "3102d.png",
        "width": 68,
        "height": 58,
        "x": 176,
        "y": 224,
        "z": 850
      }
    ],
    "icon": "gunblader/belt/3102.png"
  },
  {
    "code": "3103",
    "name": "化装舞会凯恩白色双剑",
    "images": [
      {
        "name": "3103c.png",
        "width": 1,
        "height": 1,
        "x": 500,
        "y": 0,
        "z": 1950
      },
      {
        "name": "3103d.png",
        "width": 68,
        "height": 58,
        "x": 176,
        "y": 224,
        "z": 850
      }
    ],
    "icon": "gunblader/belt/3103.png"
  },
  {
    "code": "3200",
    "name": "铁血统帅天门谣腰带[A款]",
    "images": [
      {
        "name": "3200a.png",
        "width": 19,
        "height": 5,
        "x": 212,
        "y": 234,
        "z": 1700
      }
    ],
    "icon": "gunblader/belt/3200.png"
  },
  {
    "code": "3201",
    "name": "铁血统帅天门谣腰带[B款]",
    "images": [
      {
        "name": "3201a.png",
        "width": 19,
        "height": 5,
        "x": 212,
        "y": 234,
        "z": 1700
      }
    ],
    "icon": "gunblader/belt/3201.png"
  },
  {
    "code": "3202",
    "name": "铁血统帅天门谣腰带[C款]",
    "images": [
      {
        "name": "3202a.png",
        "width": 19,
        "height": 5,
        "x": 212,
        "y": 234,
        "z": 1700
      }
    ],
    "icon": "gunblader/belt/3202.png"
  },
  {
    "code": "3203",
    "name": "铁血统帅天门谣腰带[D款]",
    "images": [
      {
        "name": "3203a.png",
        "width": 19,
        "height": 5,
        "x": 212,
        "y": 234,
        "z": 1700
      }
    ],
    "icon": "gunblader/belt/3203.png"
  },
  {
    "code": "3300",
    "name": "巅峰狂徒霜叶飞腰带[A款]",
    "images": [
      {
        "name": "3300c.png",
        "width": 29,
        "height": 18,
        "x": 204,
        "y": 232,
        "z": 1950
      },
      {
        "name": "3300d.png",
        "width": 31,
        "height": 17,
        "x": 204,
        "y": 230,
        "z": 850
      }
    ],
    "icon": "gunblader/belt/3300.png"
  },
  {
    "code": "3301",
    "name": "巅峰狂徒霜叶飞腰带[B款]",
    "images": [
      {
        "name": "3301c.png",
        "width": 29,
        "height": 18,
        "x": 204,
        "y": 232,
        "z": 1950
      },
      {
        "name": "3301d.png",
        "width": 31,
        "height": 17,
        "x": 204,
        "y": 230,
        "z": 850
      }
    ],
    "icon": "gunblader/belt/3301.png"
  },
  {
    "code": "3302",
    "name": "巅峰狂徒霜叶飞腰带[C款]",
    "images": [
      {
        "name": "3302c.png",
        "width": 29,
        "height": 18,
        "x": 204,
        "y": 232,
        "z": 1950
      },
      {
        "name": "3302d.png",
        "width": 31,
        "height": 17,
        "x": 204,
        "y": 230,
        "z": 850
      }
    ],
    "icon": "gunblader/belt/3302.png"
  },
  {
    "code": "3303",
    "name": "巅峰狂徒霜叶飞腰带[D款]",
    "images": [
      {
        "name": "3303c.png",
        "width": 29,
        "height": 18,
        "x": 204,
        "y": 232,
        "z": 1950
      },
      {
        "name": "3303d.png",
        "width": 31,
        "height": 17,
        "x": 204,
        "y": 230,
        "z": 850
      }
    ],
    "icon": "gunblader/belt/3303.png"
  },
  {
    "code": "3400",
    "name": "槿花之语青绿腰坠",
    "images": [
      {
        "name": "3400c.png",
        "width": 5,
        "height": 39,
        "x": 214,
        "y": 236,
        "z": 1950
      },
      {
        "name": "3400d.png",
        "width": 1,
        "height": 1,
        "x": 500,
        "y": 0,
        "z": 850
      }
    ],
    "icon": "gunblader/belt/3400.png"
  },
  {
    "code": "3401",
    "name": "槿花之语蓝色腰坠",
    "images": [
      {
        "name": "3401c.png",
        "width": 5,
        "height": 39,
        "x": 214,
        "y": 236,
        "z": 1950
      },
      {
        "name": "3401d.png",
        "width": 1,
        "height": 1,
        "x": 500,
        "y": 0,
        "z": 850
      }
    ],
    "icon": "gunblader/belt/3401.png"
  },
  {
    "code": "3402",
    "name": "槿花之语暗绿腰坠",
    "images": [
      {
        "name": "3402c.png",
        "width": 5,
        "height": 39,
        "x": 214,
        "y": 236,
        "z": 1950
      },
      {
        "name": "3402d.png",
        "width": 1,
        "height": 1,
        "x": 500,
        "y": 0,
        "z": 850
      }
    ],
    "icon": "gunblader/belt/3402.png"
  },
  {
    "code": "3403",
    "name": "槿花之语金黄腰坠",
    "images": [
      {
        "name": "3403c.png",
        "width": 5,
        "height": 39,
        "x": 214,
        "y": 236,
        "z": 1950
      },
      {
        "name": "3403d.png",
        "width": 1,
        "height": 1,
        "x": 500,
        "y": 0,
        "z": 850
      }
    ],
    "icon": "gunblader/belt/3403.png"
  },
  {
    "code": "3500",
    "name": "小鹿腰饰",
    "images": [
      {
        "name": "3500c.png",
        "width": 17,
        "height": 25,
        "x": 216,
        "y": 215,
        "z": 1950
      },
      {
        "name": "3500d.png",
        "width": 16,
        "height": 25,
        "x": 217,
        "y": 215,
        "z": 850
      }
    ],
    "icon": "gunblader/belt/3500.png"
  },
  {
    "code": "3600",
    "name": "怒海霸主黑色腰带",
    "images": [
      {
        "name": "3600c.png",
        "width": 40,
        "height": 61,
        "x": 192,
        "y": 230,
        "z": 1950
      },
      {
        "name": "3600d.png",
        "width": 1,
        "height": 1,
        "x": 500,
        "y": 0,
        "z": 850
      }
    ],
    "icon": "gunblader/belt/3600.png"
  },
  {
    "code": "3601",
    "name": "怒海霸主红色腰带",
    "images": [
      {
        "name": "3601c.png",
        "width": 40,
        "height": 61,
        "x": 192,
        "y": 230,
        "z": 1950
      },
      {
        "name": "3601d.png",
        "width": 1,
        "height": 1,
        "x": 500,
        "y": 0,
        "z": 850
      }
    ],
    "icon": "gunblader/belt/3601.png"
  },
  {
    "code": "3602",
    "name": "怒海霸主蓝色腰带",
    "images": [
      {
        "name": "3602c.png",
        "width": 40,
        "height": 61,
        "x": 192,
        "y": 230,
        "z": 1950
      },
      {
        "name": "3602d.png",
        "width": 1,
        "height": 1,
        "x": 500,
        "y": 0,
        "z": 850
      }
    ],
    "icon": "gunblader/belt/3602.png"
  },
  {
    "code": "3603",
    "name": "怒海霸主暗绿腰带",
    "images": [
      {
        "name": "3603c.png",
        "width": 40,
        "height": 61,
        "x": 192,
        "y": 230,
        "z": 1950
      },
      {
        "name": "3603d.png",
        "width": 1,
        "height": 1,
        "x": 500,
        "y": 0,
        "z": 850
      }
    ],
    "icon": "gunblader/belt/3603.png"
  },
  {
    "code": "3700",
    "name": "阿拉德冲浪透明腰带",
    "images": [
      {
        "name": "3700c.png",
        "width": 1,
        "height": 1,
        "x": 500,
        "y": 0,
        "z": 1950
      }
    ],
    "icon": "gunblader/belt/3700.png"
  },
  {
    "code": "7300",
    "name": "猎杀之夜腰带",
    "images": [
      {
        "name": "7300c.png",
        "width": 1,
        "height": 1,
        "x": 500,
        "y": 0,
        "z": 1950
      },
      {
        "name": "7300d.png",
        "width": 1,
        "height": 1,
        "x": 500,
        "y": 0,
        "z": 850
      },
      {
        "name": "7300a.png",
        "width": 20,
        "height": 8,
        "x": 211,
        "y": 232,
        "z": 1700
      }
    ],
    "icon": "gunblader/belt/7300.png"
  },
  {
    "code": "7400",
    "images": [
      {
        "name": "7400a.png",
        "width": 1,
        "height": 1,
        "x": 500,
        "y": 0,
        "z": 1700
      },
      {
        "name": "7400c.png",
        "width": 58,
        "height": 92,
        "x": 180,
        "y": 229,
        "z": 1950
      },
      {
        "name": "7400d.png",
        "width": 56,
        "height": 59,
        "x": 191,
        "y": 254,
        "z": 850
      }
    ],
    "icon": "gunblader/belt/7400.png"
  },
  {
    "code": "3800",
    "name": "疾风祸斗腰饰",
    "images": [
      {
        "name": "3800c.png",
        "width": 28,
        "height": 51,
        "x": 204,
        "y": 227,
        "z": 1950
      },
      {
        "name": "3800d.png",
        "width": 4,
        "height": 8,
        "x": 205,
        "y": 246,
        "z": 850
      }
    ],
    "icon": "gunblader/belt/3800.png"
  },
  {
    "code": "4000",
    "name": "暗黑桀然飞龙腰甲",
    "images": [
      {
        "name": "4000c.png",
        "width": 34,
        "height": 86,
        "x": 203,
        "y": 223,
        "z": 1950
      },
      {
        "name": "4000d.png",
        "width": 1,
        "height": 1,
        "x": 232,
        "y": 255,
        "z": 850
      }
    ],
    "icon": "gunblader/belt/4000.png"
  },
  {
    "code": "4001",
    "name": "黄金桀然飞龙腰甲",
    "images": [
      {
        "name": "4001c.png",
        "width": 34,
        "height": 86,
        "x": 203,
        "y": 223,
        "z": 1950
      },
      {
        "name": "4001d.png",
        "width": 1,
        "height": 1,
        "x": 232,
        "y": 255,
        "z": 850
      }
    ],
    "icon": "gunblader/belt/4001.png"
  },
  {
    "code": "4002",
    "name": "白银桀然飞龙腰甲",
    "images": [
      {
        "name": "4002c.png",
        "width": 34,
        "height": 86,
        "x": 203,
        "y": 223,
        "z": 1950
      },
      {
        "name": "4002d.png",
        "width": 1,
        "height": 1,
        "x": 232,
        "y": 255,
        "z": 850
      }
    ],
    "icon": "gunblader/belt/4002.png"
  },
  {
    "code": "4003",
    "name": "白金桀然飞龙腰甲",
    "images": [
      {
        "name": "4003c.png",
        "width": 34,
        "height": 86,
        "x": 203,
        "y": 223,
        "z": 1950
      },
      {
        "name": "4003d.png",
        "width": 1,
        "height": 1,
        "x": 232,
        "y": 255,
        "z": 850
      }
    ],
    "icon": "gunblader/belt/4003.png"
  },
  {
    "code": "4004",
    "name": "苍蓝桀然飞龙腰甲",
    "images": [
      {
        "name": "4004c.png",
        "width": 34,
        "height": 86,
        "x": 203,
        "y": 223,
        "z": 1950
      },
      {
        "name": "4004d.png",
        "width": 1,
        "height": 1,
        "x": 232,
        "y": 255,
        "z": 850
      }
    ],
    "icon": "gunblader/belt/4004.png"
  },
  {
    "code": "4006",
    "name": "冰凌傲视无双腰甲",
    "images": [
      {
        "name": "4006c.png",
        "width": 34,
        "height": 86,
        "x": 203,
        "y": 223,
        "z": 1950
      },
      {
        "name": "4006d.png",
        "width": 1,
        "height": 1,
        "x": 232,
        "y": 255,
        "z": 850
      }
    ],
    "icon": "gunblader/belt/4006.png"
  },
  {
    "code": "4200",
    "name": "征服者卡西利亚斯战伐腰带[A款]",
    "images": [
      {
        "name": "4200c.png",
        "width": 91,
        "height": 81,
        "x": 166,
        "y": 234,
        "z": 1950
      },
      {
        "name": "4200d.png",
        "width": 73,
        "height": 87,
        "x": 182,
        "y": 219,
        "z": 850
      }
    ],
    "icon": "gunblader/belt/4200.png"
  },
  {
    "code": "4201",
    "name": "征服者卡西利亚斯战伐腰带[B款]",
    "images": [
      {
        "name": "4201c.png",
        "width": 91,
        "height": 81,
        "x": 166,
        "y": 234,
        "z": 1950
      },
      {
        "name": "4201d.png",
        "width": 73,
        "height": 87,
        "x": 182,
        "y": 219,
        "z": 850
      }
    ],
    "icon": "gunblader/belt/4201.png"
  },
  {
    "code": "4202",
    "name": "征服者卡西利亚斯战伐腰带[C款]",
    "images": [
      {
        "name": "4202c.png",
        "width": 91,
        "height": 81,
        "x": 166,
        "y": 234,
        "z": 1950
      },
      {
        "name": "4202d.png",
        "width": 73,
        "height": 87,
        "x": 182,
        "y": 219,
        "z": 850
      }
    ],
    "icon": "gunblader/belt/4202.png"
  },
  {
    "code": "4203",
    "name": "征服者卡西利亚斯战伐腰带[D款]",
    "images": [
      {
        "name": "4203c.png",
        "width": 91,
        "height": 81,
        "x": 166,
        "y": 234,
        "z": 1950
      },
      {
        "name": "4203d.png",
        "width": 73,
        "height": 87,
        "x": 182,
        "y": 219,
        "z": 850
      }
    ],
    "icon": "gunblader/belt/4203.png"
  },
  {
    "code": "4300",
    "name": "瑞鼠律动红色腰饰 (枪剑士)",
    "images": [
      {
        "name": "4300c.png",
        "width": 26,
        "height": 16,
        "x": 210,
        "y": 222,
        "z": 1950
      },
      {
        "name": "4300d.png",
        "width": 37,
        "height": 35,
        "x": 175,
        "y": 216,
        "z": 850
      }
    ],
    "icon": "gunblader/belt/4300.png"
  },
  {
    "code": "4301",
    "name": "瑞鼠律动蓝色腰饰 (枪剑士)",
    "images": [
      {
        "name": "4301c.png",
        "width": 26,
        "height": 16,
        "x": 210,
        "y": 222,
        "z": 1950
      },
      {
        "name": "4301d.png",
        "width": 37,
        "height": 35,
        "x": 175,
        "y": 216,
        "z": 850
      }
    ],
    "icon": "gunblader/belt/4301.png"
  },
  {
    "code": "4400",
    "name": "坚定维京战士腰带[A款]",
    "images": [
      {
        "name": "4400c.png",
        "width": 51,
        "height": 51,
        "x": 188,
        "y": 231,
        "z": 1950
      }
    ],
    "icon": "gunblader/belt/4400.png"
  },
  {
    "code": "4401",
    "name": "坚定维京战士腰带[B款]",
    "images": [
      {
        "name": "4401c.png",
        "width": 51,
        "height": 51,
        "x": 188,
        "y": 231,
        "z": 1950
      }
    ],
    "icon": "gunblader/belt/4401.png"
  },
  {
    "code": "4402",
    "name": "坚定维京战士腰带[C款]",
    "images": [
      {
        "name": "4402c.png",
        "width": 51,
        "height": 51,
        "x": 188,
        "y": 231,
        "z": 1950
      }
    ],
    "icon": "gunblader/belt/4402.png"
  },
  {
    "code": "4403",
    "name": "坚定维京战士腰带[D款]",
    "images": [
      {
        "name": "4403c.png",
        "width": 51,
        "height": 51,
        "x": 188,
        "y": 231,
        "z": 1950
      }
    ],
    "icon": "gunblader/belt/4403.png"
  },
  {
    "code": "4404",
    "name": "坚定维京战士腰带[E款]",
    "images": [
      {
        "name": "4404c.png",
        "width": 51,
        "height": 51,
        "x": 188,
        "y": 231,
        "z": 1950
      }
    ],
    "icon": "gunblader/belt/4404.png"
  },
  {
    "code": "4405",
    "name": "坚定维京战士腰带[F款]",
    "images": [
      {
        "name": "4405c.png",
        "width": 51,
        "height": 51,
        "x": 188,
        "y": 231,
        "z": 1950
      }
    ],
    "icon": "gunblader/belt/4405.png"
  },
  {
    "code": "4500",
    "name": "矫捷忍法帖黑色腰带",
    "images": [
      {
        "name": "4500c.png",
        "width": 22,
        "height": 17,
        "x": 211,
        "y": 227,
        "z": 1950
      },
      {
        "name": "4500d.png",
        "width": 6,
        "height": 42,
        "x": 232,
        "y": 244,
        "z": 850
      }
    ],
    "icon": "gunblader/belt/4500.png"
  },
  {
    "code": "4501",
    "name": "矫捷忍法帖红色腰带",
    "images": [
      {
        "name": "4501c.png",
        "width": 22,
        "height": 17,
        "x": 211,
        "y": 227,
        "z": 1950
      },
      {
        "name": "4501d.png",
        "width": 6,
        "height": 42,
        "x": 232,
        "y": 244,
        "z": 850
      }
    ],
    "icon": "gunblader/belt/4501.png"
  },
  {
    "code": "4502",
    "name": "矫捷忍法帖白色腰带",
    "images": [
      {
        "name": "4502c.png",
        "width": 22,
        "height": 17,
        "x": 211,
        "y": 227,
        "z": 1950
      },
      {
        "name": "4502d.png",
        "width": 6,
        "height": 42,
        "x": 232,
        "y": 244,
        "z": 850
      }
    ],
    "icon": "gunblader/belt/4502.png"
  },
  {
    "code": "4700",
    "name": "热血学院制式腰带[A款]",
    "images": [
      {
        "name": "4700a.png",
        "width": 20,
        "height": 7,
        "x": 212,
        "y": 235,
        "z": 1700
      }
    ],
    "icon": "gunblader/belt/4700.png"
  },
  {
    "code": "4701",
    "name": "热血学院制式腰带[B款]",
    "images": [
      {
        "name": "4701a.png",
        "width": 20,
        "height": 7,
        "x": 212,
        "y": 235,
        "z": 1700
      }
    ],
    "icon": "gunblader/belt/4701.png"
  },
  {
    "code": "4702",
    "name": "热血学院制式腰带[C款]",
    "images": [
      {
        "name": "4702a.png",
        "width": 20,
        "height": 7,
        "x": 212,
        "y": 235,
        "z": 1700
      }
    ],
    "icon": "gunblader/belt/4702.png"
  },
  {
    "code": "4703",
    "name": "热血学院制式腰带[D款]",
    "images": [
      {
        "name": "4703a.png",
        "width": 20,
        "height": 7,
        "x": 212,
        "y": 235,
        "z": 1700
      }
    ],
    "icon": "gunblader/belt/4703.png"
  },
  {
    "code": "4800",
    "name": "梦幻cos-博肯包袱[A款]",
    "images": [
      {
        "name": "4800c.png",
        "width": 1,
        "height": 1,
        "x": 500,
        "y": 0,
        "z": 1950
      },
      {
        "name": "4800d.png",
        "width": 29,
        "height": 16,
        "x": 204,
        "y": 230,
        "z": 850
      }
    ],
    "icon": "gunblader/belt/4800.png"
  },
  {
    "code": "4801",
    "name": "梦幻cos-博肯包袱[B款]",
    "images": [
      {
        "name": "4801c.png",
        "width": 1,
        "height": 1,
        "x": 500,
        "y": 0,
        "z": 1950
      },
      {
        "name": "4801d.png",
        "width": 29,
        "height": 16,
        "x": 204,
        "y": 230,
        "z": 850
      }
    ],
    "icon": "gunblader/belt/4801.png"
  },
  {
    "code": "4802",
    "name": "梦幻cos-博肯包袱[C款]",
    "images": [
      {
        "name": "4802c.png",
        "width": 1,
        "height": 1,
        "x": 500,
        "y": 0,
        "z": 1950
      },
      {
        "name": "4802d.png",
        "width": 29,
        "height": 16,
        "x": 204,
        "y": 230,
        "z": 850
      }
    ],
    "icon": "gunblader/belt/4802.png"
  },
  {
    "code": "4803",
    "name": "梦幻cos-博肯包袱[D款]",
    "images": [
      {
        "name": "4803c.png",
        "width": 1,
        "height": 1,
        "x": 500,
        "y": 0,
        "z": 1950
      },
      {
        "name": "4803d.png",
        "width": 29,
        "height": 16,
        "x": 204,
        "y": 230,
        "z": 850
      }
    ],
    "icon": "gunblader/belt/4803.png"
  },
  {
    "code": "4900",
    "name": "榛子巧克力奶油腰带",
    "images": [
      {
        "name": "4900b.png",
        "width": 1,
        "height": 1,
        "x": 500,
        "y": 0,
        "z": 1100
      },
      {
        "name": "4900c.png",
        "width": 12,
        "height": 14,
        "x": 207,
        "y": 225,
        "z": 1950
      }
    ],
    "icon": "gunblader/belt/4900.png"
  },
  {
    "code": "4901",
    "name": "香草巧克力奶油腰带",
    "images": [
      {
        "name": "4901b.png",
        "width": 1,
        "height": 1,
        "x": 500,
        "y": 0,
        "z": 1100
      },
      {
        "name": "4901c.png",
        "width": 12,
        "height": 14,
        "x": 207,
        "y": 225,
        "z": 1950
      }
    ],
    "icon": "gunblader/belt/4901.png"
  },
  {
    "code": "4902",
    "name": "牛奶巧克力奶油腰带",
    "images": [
      {
        "name": "4902b.png",
        "width": 1,
        "height": 1,
        "x": 500,
        "y": 0,
        "z": 1100
      },
      {
        "name": "4902c.png",
        "width": 12,
        "height": 14,
        "x": 207,
        "y": 225,
        "z": 1950
      }
    ],
    "icon": "gunblader/belt/4902.png"
  },
  {
    "code": "5000",
    "name": "星光誓约婚礼腰饰",
    "images": [
      {
        "name": "5000c.png",
        "width": 13,
        "height": 16,
        "x": 207,
        "y": 231,
        "z": 1950
      },
      {
        "name": "5000d.png",
        "width": 1,
        "height": 1,
        "x": 500,
        "y": 0,
        "z": 850
      }
    ],
    "icon": "gunblader/belt/5000.png"
  },
  {
    "code": "5100",
    "name": "混沌长虹凌天腰饰",
    "images": [
      {
        "name": "5100c.png",
        "width": 28,
        "height": 50,
        "x": 207,
        "y": 226,
        "z": 1950
      },
      {
        "name": "5100d.png",
        "width": 1,
        "height": 1,
        "x": 500,
        "y": 0,
        "z": 850
      }
    ],
    "icon": "gunblader/belt/5100.png"
  },
  {
    "code": "5101",
    "name": "光明长虹凌天腰饰",
    "images": [
      {
        "name": "5101c.png",
        "width": 28,
        "height": 50,
        "x": 207,
        "y": 226,
        "z": 1950
      },
      {
        "name": "5101d.png",
        "width": 1,
        "height": 1,
        "x": 500,
        "y": 0,
        "z": 850
      }
    ],
    "icon": "gunblader/belt/5101.png"
  },
  {
    "code": "5200",
    "name": "塞勒盖尔的腰带[A款]",
    "images": [
      {
        "name": "5200a.png",
        "width": 21,
        "height": 9,
        "x": 211,
        "y": 232,
        "z": 1700
      }
    ],
    "icon": "gunblader/belt/5200.png"
  },
  {
    "code": "5201",
    "name": "塞勒盖尔的腰带[B款]",
    "images": [
      {
        "name": "5201a.png",
        "width": 21,
        "height": 9,
        "x": 211,
        "y": 232,
        "z": 1700
      }
    ],
    "icon": "gunblader/belt/5201.png"
  },
  {
    "code": "5202",
    "name": "塞勒盖尔的腰带[C款]",
    "images": [
      {
        "name": "5202a.png",
        "width": 21,
        "height": 9,
        "x": 211,
        "y": 232,
        "z": 1700
      }
    ],
    "icon": "gunblader/belt/5202.png"
  },
  {
    "code": "5203",
    "name": "塞勒盖尔的腰带[D款]",
    "images": [
      {
        "name": "5203a.png",
        "width": 21,
        "height": 9,
        "x": 211,
        "y": 232,
        "z": 1700
      }
    ],
    "icon": "gunblader/belt/5203.png"
  },
  {
    "code": "5300",
    "name": "神圣光翼天使腰甲",
    "images": [
      {
        "name": "5300c.png",
        "width": 69,
        "height": 100,
        "x": 178,
        "y": 228,
        "z": 1950
      },
      {
        "name": "5300d.png",
        "width": 40,
        "height": 50,
        "x": 198,
        "y": 259,
        "z": 850
      }
    ],
    "icon": "gunblader/belt/5300.png"
  },
  {
    "code": "5400",
    "name": "骄阳骑士明旭腰带",
    "images": [
      {
        "name": "5400c.png",
        "width": 29,
        "height": 49,
        "x": 206,
        "y": 229,
        "z": 1950
      },
      {
        "name": "5400d.png",
        "width": 1,
        "height": 1,
        "x": 500,
        "y": 0,
        "z": 850
      }
    ],
    "icon": "gunblader/belt/5400.png"
  },
  {
    "code": "5401",
    "name": "银月骑士明旭腰带",
    "images": [
      {
        "name": "5401c.png",
        "width": 29,
        "height": 49,
        "x": 206,
        "y": 229,
        "z": 1950
      },
      {
        "name": "5401d.png",
        "width": 1,
        "height": 1,
        "x": 500,
        "y": 0,
        "z": 850
      }
    ],
    "icon": "gunblader/belt/5401.png"
  },
  {
    "code": "5500",
    "name": "萨克沙敏捷腰甲[A款]",
    "images": [
      {
        "name": "5500c.png",
        "width": 28,
        "height": 30,
        "x": 205,
        "y": 231,
        "z": 1950
      },
      {
        "name": "5500d.png",
        "width": 1,
        "height": 1,
        "x": 500,
        "y": 0,
        "z": 850
      }
    ],
    "icon": "gunblader/belt/5500.png"
  },
  {
    "code": "5501",
    "name": "萨克沙敏捷腰甲[B款]",
    "images": [
      {
        "name": "5501c.png",
        "width": 28,
        "height": 30,
        "x": 205,
        "y": 231,
        "z": 1950
      },
      {
        "name": "5501d.png",
        "width": 1,
        "height": 1,
        "x": 500,
        "y": 0,
        "z": 850
      }
    ],
    "icon": "gunblader/belt/5501.png"
  },
  {
    "code": "5502",
    "name": "萨克沙敏捷腰甲[C款]",
    "images": [
      {
        "name": "5502c.png",
        "width": 28,
        "height": 30,
        "x": 205,
        "y": 231,
        "z": 1950
      },
      {
        "name": "5502d.png",
        "width": 1,
        "height": 1,
        "x": 500,
        "y": 0,
        "z": 850
      }
    ],
    "icon": "gunblader/belt/5502.png"
  },
  {
    "code": "5503",
    "name": "萨克沙敏捷腰甲[D款]",
    "images": [
      {
        "name": "5503c.png",
        "width": 28,
        "height": 30,
        "x": 205,
        "y": 231,
        "z": 1950
      },
      {
        "name": "5503d.png",
        "width": 1,
        "height": 1,
        "x": 500,
        "y": 0,
        "z": 850
      }
    ],
    "icon": "gunblader/belt/5503.png"
  },
  {
    "code": "5700",
    "images": [
      {
        "name": "5700c.png",
        "width": 1,
        "height": 1,
        "x": 500,
        "y": 0,
        "z": 1950
      },
      {
        "name": "5700d.png",
        "width": 37,
        "height": 42,
        "x": 175,
        "y": 236,
        "z": 850
      }
    ],
    "icon": "gunblader/belt/5700.png"
  },
  {
    "code": "5701",
    "images": [
      {
        "name": "5701c.png",
        "width": 1,
        "height": 1,
        "x": 500,
        "y": 0,
        "z": 1950
      },
      {
        "name": "5701d.png",
        "width": 37,
        "height": 42,
        "x": 175,
        "y": 236,
        "z": 850
      }
    ],
    "icon": "gunblader/belt/5701.png"
  },
  {
    "code": "5703",
    "images": [
      {
        "name": "5703c.png",
        "width": 1,
        "height": 1,
        "x": 500,
        "y": 0,
        "z": 1950
      },
      {
        "name": "5703d.png",
        "width": 37,
        "height": 42,
        "x": 175,
        "y": 236,
        "z": 850
      }
    ],
    "icon": "gunblader/belt/5703.png"
  },
  {
    "code": "5702",
    "images": [
      {
        "name": "5702c.png",
        "width": 1,
        "height": 1,
        "x": 500,
        "y": 0,
        "z": 1950
      },
      {
        "name": "5702d.png",
        "width": 37,
        "height": 42,
        "x": 175,
        "y": 236,
        "z": 850
      }
    ],
    "icon": "gunblader/belt/5702.png"
  },
  {
    "code": "5704",
    "images": [
      {
        "name": "5704c.png",
        "width": 1,
        "height": 1,
        "x": 500,
        "y": 0,
        "z": 1950
      },
      {
        "name": "5704d.png",
        "width": 37,
        "height": 42,
        "x": 175,
        "y": 236,
        "z": 850
      }
    ],
    "icon": "gunblader/belt/5704.png"
  },
  {
    "code": "5800",
    "name": "桀骜王者高贵腰带",
    "images": [
      {
        "name": "5800c.png",
        "width": 24,
        "height": 31,
        "x": 208,
        "y": 230,
        "z": 1950
      },
      {
        "name": "5800d.png",
        "width": 46,
        "height": 74,
        "x": 195,
        "y": 227,
        "z": 850
      }
    ],
    "icon": "gunblader/belt/5800.png"
  },
  {
    "code": "5900",
    "name": "绚丽晴夏酷爽脐钉[A款]",
    "images": [
      {
        "name": "5900d.png",
        "width": 3,
        "height": 6,
        "x": 222,
        "y": 229,
        "z": 850
      }
    ],
    "icon": "gunblader/belt/5900.png"
  },
  {
    "code": "5901",
    "name": "绚丽晴夏酷爽脐钉[B款]",
    "images": [
      {
        "name": "5901d.png",
        "width": 3,
        "height": 6,
        "x": 222,
        "y": 229,
        "z": 850
      }
    ],
    "icon": "gunblader/belt/5901.png"
  },
  {
    "code": "5902",
    "name": "绚丽晴夏酷爽脐钉[C款]",
    "images": [
      {
        "name": "5902d.png",
        "width": 3,
        "height": 6,
        "x": 222,
        "y": 229,
        "z": 850
      }
    ],
    "icon": "gunblader/belt/5902.png"
  },
  {
    "code": "5903",
    "name": "绚丽晴夏酷爽脐钉[D款]",
    "images": [
      {
        "name": "5903d.png",
        "width": 3,
        "height": 6,
        "x": 222,
        "y": 229,
        "z": 850
      }
    ],
    "icon": "gunblader/belt/5903.png"
  },
  {
    "code": "6000",
    "name": "浪漫年华绅士拐杖[A款]",
    "images": [
      {
        "name": "6000c.png",
        "width": 1,
        "height": 1,
        "x": 500,
        "y": 0,
        "z": 1950
      },
      {
        "name": "6000d.png",
        "width": 55,
        "height": 56,
        "x": 190,
        "y": 228,
        "z": 850
      }
    ],
    "icon": "gunblader/belt/6000.png"
  },
  {
    "code": "6001",
    "name": "浪漫年华绅士拐杖[B款]",
    "images": [
      {
        "name": "6001c.png",
        "width": 1,
        "height": 1,
        "x": 500,
        "y": 0,
        "z": 1950
      },
      {
        "name": "6001d.png",
        "width": 55,
        "height": 56,
        "x": 190,
        "y": 228,
        "z": 850
      }
    ],
    "icon": "gunblader/belt/6001.png"
  },
  {
    "code": "6002",
    "name": "浪漫年华绅士拐杖[C款]",
    "images": [
      {
        "name": "6002c.png",
        "width": 1,
        "height": 1,
        "x": 500,
        "y": 0,
        "z": 1950
      },
      {
        "name": "6002d.png",
        "width": 55,
        "height": 56,
        "x": 190,
        "y": 228,
        "z": 850
      }
    ],
    "icon": "gunblader/belt/6002.png"
  },
  {
    "code": "6003",
    "name": "浪漫年华绅士拐杖[D款]",
    "images": [
      {
        "name": "6003c.png",
        "width": 1,
        "height": 1,
        "x": 500,
        "y": 0,
        "z": 1950
      },
      {
        "name": "6003d.png",
        "width": 55,
        "height": 56,
        "x": 190,
        "y": 228,
        "z": 850
      }
    ],
    "icon": "gunblader/belt/6003.png"
  },
  {
    "code": "6200",
    "name": "艾伦坚定之誓腰带",
    "images": [
      {
        "name": "6200c.png",
        "width": 24,
        "height": 22,
        "x": 208,
        "y": 228,
        "z": 1950
      },
      {
        "name": "6200d.png",
        "width": 1,
        "height": 1,
        "x": 500,
        "y": 0,
        "z": 850
      }
    ],
    "icon": "gunblader/belt/6200.png"
  },
  {
    "code": "6300",
    "name": "信奘坚定之誓腰带",
    "images": [
      {
        "name": "6300c.png",
        "width": 47,
        "height": 70,
        "x": 192,
        "y": 229,
        "z": 1950
      },
      {
        "name": "6300d.png",
        "width": 40,
        "height": 39,
        "x": 193,
        "y": 259,
        "z": 850
      }
    ],
    "icon": "gunblader/belt/6300.png"
  },
  {
    "code": "6400",
    "name": "临界飞跃腰带[A款]",
    "images": [
      {
        "name": "6400a.png",
        "width": 28,
        "height": 42,
        "x": 206,
        "y": 231,
        "z": 1700
      },
      {
        "name": "6400d.png",
        "width": 25,
        "height": 52,
        "x": 208,
        "y": 243,
        "z": 850
      }
    ],
    "icon": "gunblader/belt/6400.png"
  },
  {
    "code": "6401",
    "name": "临界飞跃腰带[B款]",
    "images": [
      {
        "name": "6401a.png",
        "width": 28,
        "height": 42,
        "x": 206,
        "y": 231,
        "z": 1700
      },
      {
        "name": "6401d.png",
        "width": 25,
        "height": 52,
        "x": 208,
        "y": 243,
        "z": 850
      }
    ],
    "icon": "gunblader/belt/6401.png"
  },
  {
    "code": "6402",
    "name": "临界飞跃腰带[C款]",
    "images": [
      {
        "name": "6402a.png",
        "width": 28,
        "height": 42,
        "x": 206,
        "y": 231,
        "z": 1700
      },
      {
        "name": "6402d.png",
        "width": 25,
        "height": 52,
        "x": 208,
        "y": 243,
        "z": 850
      }
    ],
    "icon": "gunblader/belt/6402.png"
  },
  {
    "code": "6403",
    "name": "临界飞跃腰带[D款]",
    "images": [
      {
        "name": "6403a.png",
        "width": 28,
        "height": 42,
        "x": 206,
        "y": 231,
        "z": 1700
      },
      {
        "name": "6403d.png",
        "width": 25,
        "height": 52,
        "x": 208,
        "y": 243,
        "z": 850
      }
    ],
    "icon": "gunblader/belt/6403.png"
  },
  {
    "code": "6404",
    "name": "临界飞跃腰带[E款]",
    "images": [
      {
        "name": "6404a.png",
        "width": 28,
        "height": 42,
        "x": 206,
        "y": 231,
        "z": 1700
      },
      {
        "name": "6404d.png",
        "width": 25,
        "height": 52,
        "x": 208,
        "y": 243,
        "z": 850
      }
    ],
    "icon": "gunblader/belt/6404.png"
  },
  {
    "code": "6600",
    "name": "精灵英雄之歌木纹腰带[A款]",
    "images": [
      {
        "name": "6600c.png",
        "width": 34,
        "height": 60,
        "x": 200,
        "y": 231,
        "z": 1950
      },
      {
        "name": "6600d.png",
        "width": 1,
        "height": 1,
        "x": 500,
        "y": 0,
        "z": 850
      }
    ],
    "icon": "gunblader/belt/6600.png"
  },
  {
    "code": "6601",
    "name": "精灵英雄之歌木纹腰带[B款]",
    "images": [
      {
        "name": "6601c.png",
        "width": 34,
        "height": 60,
        "x": 200,
        "y": 231,
        "z": 1950
      },
      {
        "name": "6601d.png",
        "width": 1,
        "height": 1,
        "x": 500,
        "y": 0,
        "z": 850
      }
    ],
    "icon": "gunblader/belt/6601.png"
  },
  {
    "code": "6602",
    "name": "精灵英雄之歌木纹腰带[C款]",
    "images": [
      {
        "name": "6602c.png",
        "width": 34,
        "height": 60,
        "x": 200,
        "y": 231,
        "z": 1950
      },
      {
        "name": "6602d.png",
        "width": 1,
        "height": 1,
        "x": 500,
        "y": 0,
        "z": 850
      }
    ],
    "icon": "gunblader/belt/6602.png"
  },
  {
    "code": "6603",
    "name": "精灵英雄之歌木纹腰带[D款]",
    "images": [
      {
        "name": "6603c.png",
        "width": 34,
        "height": 60,
        "x": 200,
        "y": 231,
        "z": 1950
      },
      {
        "name": "6603d.png",
        "width": 1,
        "height": 1,
        "x": 500,
        "y": 0,
        "z": 850
      }
    ],
    "icon": "gunblader/belt/6603.png"
  },
  {
    "code": "6604",
    "name": "精灵英雄之歌木纹腰带[E款]",
    "images": [
      {
        "name": "6604c.png",
        "width": 34,
        "height": 60,
        "x": 200,
        "y": 231,
        "z": 1950
      },
      {
        "name": "6604d.png",
        "width": 1,
        "height": 1,
        "x": 500,
        "y": 0,
        "z": 850
      }
    ],
    "icon": "gunblader/belt/6604.png"
  },
  {
    "code": "6700",
    "name": "如意虎冠军腰带",
    "images": [
      {
        "name": "6700c.png",
        "width": 19,
        "height": 8,
        "x": 212,
        "y": 230,
        "z": 1950
      }
    ],
    "icon": "gunblader/belt/6700.png"
  },
  {
    "code": "6701",
    "name": "威风虎冠军腰带",
    "images": [
      {
        "name": "6701c.png",
        "width": 19,
        "height": 8,
        "x": 212,
        "y": 230,
        "z": 1950
      }
    ],
    "icon": "gunblader/belt/6701.png"
  },
  {
    "code": "6800",
    "name": "苍暮·特工隐踪枪剑[款式1]",
    "images": [
      {
        "name": "6800a.png",
        "width": 23,
        "height": 22,
        "x": 209,
        "y": 235,
        "z": 1700
      },
      {
        "name": "6800c.png",
        "width": 1,
        "height": 1,
        "x": 500,
        "y": 0,
        "z": 1950
      },
      {
        "name": "6800d.png",
        "width": 25,
        "height": 47,
        "x": 215,
        "y": 231,
        "z": 850
      }
    ],
    "icon": "gunblader/belt/6800.png"
  },
  {
    "code": "6801",
    "name": "苍暮·特工隐煞枪剑[款式2]",
    "images": [
      {
        "name": "6801a.png",
        "width": 23,
        "height": 22,
        "x": 209,
        "y": 235,
        "z": 1700
      },
      {
        "name": "6801c.png",
        "width": 1,
        "height": 1,
        "x": 500,
        "y": 0,
        "z": 1950
      },
      {
        "name": "6801d.png",
        "width": 25,
        "height": 47,
        "x": 215,
        "y": 231,
        "z": 850
      }
    ],
    "icon": "gunblader/belt/6801.png"
  },
  {
    "code": "6802",
    "name": "苍暮·特工隐魂枪剑[款式3]",
    "images": [
      {
        "name": "6802a.png",
        "width": 23,
        "height": 22,
        "x": 209,
        "y": 235,
        "z": 1700
      },
      {
        "name": "6802c.png",
        "width": 1,
        "height": 1,
        "x": 500,
        "y": 0,
        "z": 1950
      },
      {
        "name": "6802d.png",
        "width": 25,
        "height": 47,
        "x": 215,
        "y": 231,
        "z": 850
      }
    ],
    "icon": "gunblader/belt/6802.png"
  },
  {
    "code": "6803",
    "name": "苍暮·特工隐灭枪剑[款式4]",
    "images": [
      {
        "name": "6803a.png",
        "width": 23,
        "height": 22,
        "x": 209,
        "y": 235,
        "z": 1700
      },
      {
        "name": "6803c.png",
        "width": 1,
        "height": 1,
        "x": 500,
        "y": 0,
        "z": 1950
      },
      {
        "name": "6803d.png",
        "width": 25,
        "height": 47,
        "x": 215,
        "y": 231,
        "z": 850
      }
    ],
    "icon": "gunblader/belt/6803.png"
  },
  {
    "code": "6804",
    "name": "苍暮·特工隐武枪剑[银色款]",
    "images": [
      {
        "name": "6804a.png",
        "width": 23,
        "height": 22,
        "x": 209,
        "y": 235,
        "z": 1700
      },
      {
        "name": "6804c.png",
        "width": 1,
        "height": 1,
        "x": 500,
        "y": 0,
        "z": 1950
      },
      {
        "name": "6804d.png",
        "width": 25,
        "height": 47,
        "x": 215,
        "y": 231,
        "z": 850
      }
    ],
    "icon": "gunblader/belt/6804.png"
  },
  {
    "code": "6805",
    "name": "苍暮·特工隐月枪剑[金色款]",
    "images": [
      {
        "name": "6805a.png",
        "width": 23,
        "height": 22,
        "x": 209,
        "y": 235,
        "z": 1700
      },
      {
        "name": "6805c.png",
        "width": 1,
        "height": 1,
        "x": 500,
        "y": 0,
        "z": 1950
      },
      {
        "name": "6805d.png",
        "width": 25,
        "height": 47,
        "x": 215,
        "y": 231,
        "z": 850
      }
    ],
    "icon": "gunblader/belt/6805.png"
  },
  {
    "code": "6900",
    "name": "苍暮·战线佣兵烽烟腰饰[款式1]",
    "images": [
      {
        "name": "6900c.png",
        "width": 38,
        "height": 42,
        "x": 199,
        "y": 229,
        "z": 1950
      },
      {
        "name": "6900d.png",
        "width": 8,
        "height": 26,
        "x": 214,
        "y": 254,
        "z": 850
      }
    ],
    "icon": "gunblader/belt/6900.png"
  },
  {
    "code": "6901",
    "name": "苍暮·战线佣兵烽爆腰饰[款式2]",
    "images": [
      {
        "name": "6901c.png",
        "width": 38,
        "height": 42,
        "x": 199,
        "y": 229,
        "z": 1950
      },
      {
        "name": "6901d.png",
        "width": 8,
        "height": 26,
        "x": 214,
        "y": 254,
        "z": 850
      }
    ],
    "icon": "gunblader/belt/6901.png"
  },
  {
    "code": "6902",
    "name": "苍暮·战线佣兵烽火腰饰[款式3]",
    "images": [
      {
        "name": "6902c.png",
        "width": 38,
        "height": 42,
        "x": 199,
        "y": 229,
        "z": 1950
      },
      {
        "name": "6902d.png",
        "width": 8,
        "height": 26,
        "x": 214,
        "y": 254,
        "z": 850
      }
    ],
    "icon": "gunblader/belt/6902.png"
  },
  {
    "code": "6903",
    "name": "苍暮·战线佣兵烽狼腰饰[款式4]",
    "images": [
      {
        "name": "6903c.png",
        "width": 38,
        "height": 42,
        "x": 199,
        "y": 229,
        "z": 1950
      },
      {
        "name": "6903d.png",
        "width": 8,
        "height": 26,
        "x": 214,
        "y": 254,
        "z": 850
      }
    ],
    "icon": "gunblader/belt/6903.png"
  },
  {
    "code": "6904",
    "name": "苍暮·战线佣兵烽魂腰饰[银色款]",
    "images": [
      {
        "name": "6904c.png",
        "width": 38,
        "height": 42,
        "x": 199,
        "y": 229,
        "z": 1950
      },
      {
        "name": "6904d.png",
        "width": 8,
        "height": 26,
        "x": 214,
        "y": 254,
        "z": 850
      }
    ],
    "icon": "gunblader/belt/6904.png"
  },
  {
    "code": "6905",
    "name": "苍暮·战线佣兵烽炎腰饰[金色款]",
    "images": [
      {
        "name": "6905c.png",
        "width": 38,
        "height": 42,
        "x": 199,
        "y": 229,
        "z": 1950
      },
      {
        "name": "6905d.png",
        "width": 8,
        "height": 26,
        "x": 214,
        "y": 254,
        "z": 850
      }
    ],
    "icon": "gunblader/belt/6905.png"
  },
  {
    "code": "7000",
    "name": "苍暮·源能专家超能腰带[款式1]",
    "images": [
      {
        "name": "7000a.png",
        "width": 20,
        "height": 11,
        "x": 211,
        "y": 232,
        "z": 1700
      }
    ],
    "icon": "gunblader/belt/7000.png"
  },
  {
    "code": "7001",
    "name": "苍暮·源能专家超域腰带[款式2]",
    "images": [
      {
        "name": "7001a.png",
        "width": 20,
        "height": 11,
        "x": 211,
        "y": 232,
        "z": 1700
      }
    ],
    "icon": "gunblader/belt/7001.png"
  },
  {
    "code": "7002",
    "name": "苍暮·源能专家超界腰带[款式3]",
    "images": [
      {
        "name": "7002a.png",
        "width": 20,
        "height": 11,
        "x": 211,
        "y": 232,
        "z": 1700
      }
    ],
    "icon": "gunblader/belt/7002.png"
  },
  {
    "code": "7003",
    "name": "苍暮·源能专家超核腰带[款式4]",
    "images": [
      {
        "name": "7003a.png",
        "width": 20,
        "height": 11,
        "x": 211,
        "y": 232,
        "z": 1700
      }
    ],
    "icon": "gunblader/belt/7003.png"
  },
  {
    "code": "7004",
    "name": "苍暮·源能专家超维腰带[银色款]",
    "images": [
      {
        "name": "7004a.png",
        "width": 20,
        "height": 11,
        "x": 211,
        "y": 232,
        "z": 1700
      }
    ],
    "icon": "gunblader/belt/7004.png"
  },
  {
    "code": "7005",
    "name": "苍暮·源能专家超星腰带[金色款]",
    "images": [
      {
        "name": "7005a.png",
        "width": 20,
        "height": 11,
        "x": 211,
        "y": 232,
        "z": 1700
      }
    ],
    "icon": "gunblader/belt/7005.png"
  },
  {
    "code": "7200",
    "name": "真龙之魄腰带[A款]",
    "images": [
      {
        "name": "7200c.png",
        "width": 51,
        "height": 70,
        "x": 192,
        "y": 231,
        "z": 1950
      },
      {
        "name": "7200d.png",
        "width": 17,
        "height": 30,
        "x": 205,
        "y": 259,
        "z": 850
      }
    ],
    "icon": "gunblader/belt/7200.png"
  },
  {
    "code": "7201",
    "name": "真龙之魄腰带[B款]",
    "images": [
      {
        "name": "7201c.png",
        "width": 51,
        "height": 70,
        "x": 192,
        "y": 231,
        "z": 1950
      },
      {
        "name": "7201d.png",
        "width": 17,
        "height": 30,
        "x": 205,
        "y": 259,
        "z": 850
      }
    ],
    "icon": "gunblader/belt/7201.png"
  },
  {
    "code": "7202",
    "name": "真龙之魄腰带[C款]",
    "images": [
      {
        "name": "7202c.png",
        "width": 51,
        "height": 70,
        "x": 192,
        "y": 231,
        "z": 1950
      },
      {
        "name": "7202d.png",
        "width": 17,
        "height": 30,
        "x": 205,
        "y": 259,
        "z": 850
      }
    ],
    "icon": "gunblader/belt/7202.png"
  },
  {
    "code": "7203",
    "name": "真龙之魄腰带[D款]",
    "images": [
      {
        "name": "7203c.png",
        "width": 51,
        "height": 70,
        "x": 192,
        "y": 231,
        "z": 1950
      },
      {
        "name": "7203d.png",
        "width": 17,
        "height": 30,
        "x": 205,
        "y": 259,
        "z": 850
      }
    ],
    "icon": "gunblader/belt/7203.png"
  },
  {
    "code": "7500",
    "name": "穿花拂柳蝴蝶腰带[A款]",
    "images": [
      {
        "name": "7500c.png",
        "width": 14,
        "height": 26,
        "x": 206,
        "y": 229,
        "z": 1950
      },
      {
        "name": "7500d.png",
        "width": 1,
        "height": 1,
        "x": 500,
        "y": 0,
        "z": 850
      }
    ],
    "icon": "gunblader/belt/7500.png"
  },
  {
    "code": "7501",
    "name": "穿花拂柳蝴蝶腰带[B款]",
    "images": [
      {
        "name": "7501c.png",
        "width": 14,
        "height": 26,
        "x": 206,
        "y": 229,
        "z": 1950
      },
      {
        "name": "7501d.png",
        "width": 1,
        "height": 1,
        "x": 500,
        "y": 0,
        "z": 850
      }
    ],
    "icon": "gunblader/belt/7501.png"
  },
  {
    "code": "7502",
    "name": "穿花拂柳蝴蝶腰带[C款]",
    "images": [
      {
        "name": "7502c.png",
        "width": 14,
        "height": 26,
        "x": 206,
        "y": 229,
        "z": 1950
      },
      {
        "name": "7502d.png",
        "width": 1,
        "height": 1,
        "x": 500,
        "y": 0,
        "z": 850
      }
    ],
    "icon": "gunblader/belt/7502.png"
  },
  {
    "code": "7503",
    "name": "穿花拂柳蝴蝶腰带[D款]",
    "images": [
      {
        "name": "7503c.png",
        "width": 14,
        "height": 26,
        "x": 206,
        "y": 229,
        "z": 1950
      },
      {
        "name": "7503d.png",
        "width": 1,
        "height": 1,
        "x": 500,
        "y": 0,
        "z": 850
      }
    ],
    "icon": "gunblader/belt/7503.png"
  },
  {
    "code": "7504",
    "name": "穿花拂柳蝴蝶腰带[E款]",
    "images": [
      {
        "name": "7504c.png",
        "width": 14,
        "height": 26,
        "x": 206,
        "y": 229,
        "z": 1950
      },
      {
        "name": "7504d.png",
        "width": 1,
        "height": 1,
        "x": 500,
        "y": 0,
        "z": 850
      }
    ],
    "icon": "gunblader/belt/7504.png"
  },
  {
    "code": "7600",
    "name": "苍暮·暗刃鹰魂手枪[款式1]",
    "images": [
      {
        "name": "7600c.png",
        "width": 30,
        "height": 31,
        "x": 204,
        "y": 231,
        "z": 1950
      },
      {
        "name": "7600d.png",
        "width": 1,
        "height": 1,
        "x": 500,
        "y": 0,
        "z": 850
      }
    ],
    "icon": "gunblader/belt/7600.png"
  },
  {
    "code": "7601",
    "name": "苍暮·暗刃鹰翼手枪[款式2]",
    "images": [
      {
        "name": "7601c.png",
        "width": 30,
        "height": 31,
        "x": 204,
        "y": 231,
        "z": 1950
      },
      {
        "name": "7601d.png",
        "width": 1,
        "height": 1,
        "x": 500,
        "y": 0,
        "z": 850
      }
    ],
    "icon": "gunblader/belt/7601.png"
  },
  {
    "code": "7602",
    "name": "苍暮·暗刃鹰灵手枪[款式3]",
    "images": [
      {
        "name": "7602c.png",
        "width": 30,
        "height": 31,
        "x": 204,
        "y": 231,
        "z": 1950
      },
      {
        "name": "7602d.png",
        "width": 1,
        "height": 1,
        "x": 500,
        "y": 0,
        "z": 850
      }
    ],
    "icon": "gunblader/belt/7602.png"
  },
  {
    "code": "7603",
    "name": "苍暮·暗刃鹰心手枪[款式4]",
    "images": [
      {
        "name": "7603c.png",
        "width": 30,
        "height": 31,
        "x": 204,
        "y": 231,
        "z": 1950
      },
      {
        "name": "7603d.png",
        "width": 1,
        "height": 1,
        "x": 500,
        "y": 0,
        "z": 850
      }
    ],
    "icon": "gunblader/belt/7603.png"
  },
  {
    "code": "7604",
    "name": "苍暮·暗刃鹰星手枪[银色款]",
    "images": [
      {
        "name": "7604c.png",
        "width": 30,
        "height": 31,
        "x": 204,
        "y": 231,
        "z": 1950
      },
      {
        "name": "7604d.png",
        "width": 1,
        "height": 1,
        "x": 500,
        "y": 0,
        "z": 850
      }
    ],
    "icon": "gunblader/belt/7604.png"
  },
  {
    "code": "7605",
    "name": "苍暮·暗刃鹰掠手枪[金色款]",
    "images": [
      {
        "name": "7605c.png",
        "width": 30,
        "height": 31,
        "x": 204,
        "y": 231,
        "z": 1950
      },
      {
        "name": "7605d.png",
        "width": 1,
        "height": 1,
        "x": 500,
        "y": 0,
        "z": 850
      }
    ],
    "icon": "gunblader/belt/7605.png"
  }
]